.git_archival.txt
.gitattributes
.gitignore
.travis.yml
CONTRIBUTING.md
LICENSE
MANIFEST.in
README.rst
meta.yaml
requirements-doc.txt
requirements.txt
setup.cfg
setup.py
.github/workflows/python-package.yaml
docs/Makefile
docs/make.bat
docs/source/api.rst
docs/source/conf.py
docs/source/credits.rst
docs/source/examples.rst
docs/source/index.rst
docs/source/zrefs.rst
docs/source/api/xdesign.acquisition.rst
docs/source/api/xdesign.codes.rst
docs/source/api/xdesign.constants.rst
docs/source/api/xdesign.formats.rst
docs/source/api/xdesign.geometry.rst
docs/source/api/xdesign.material.rst
docs/source/api/xdesign.metrics.rst
docs/source/api/xdesign.phantom.rst
docs/source/api/xdesign.plot.rst
docs/source/api/xdesign.recon.rst
docs/source/bibtex/cite.bib
docs/source/bibtex/refs.bib
docs/source/demos/FullReferenceMetrics.ipynb
docs/source/demos/NoReferenceMetrics.ipynb
docs/source/demos/Parameterized.ipynb
docs/source/demos/Shepp.ipynb
docs/source/demos/StandardPatterns.ipynb
docs/source/demos/WetCircles.ipynb
docs/source/img/xdesign-logo.png
src/xdesign/__init__.py
src/xdesign/acquisition.py
src/xdesign/codes.py
src/xdesign/constants.py
src/xdesign/formats.py
src/xdesign/material.py
src/xdesign/plot.py
src/xdesign/recon.py
src/xdesign.egg-info/PKG-INFO
src/xdesign.egg-info/SOURCES.txt
src/xdesign.egg-info/dependency_links.txt
src/xdesign.egg-info/requires.txt
src/xdesign.egg-info/top_level.txt
src/xdesign/geometry/__init__.py
src/xdesign/geometry/area.py
src/xdesign/geometry/entity.py
src/xdesign/geometry/intersect.py
src/xdesign/geometry/line.py
src/xdesign/geometry/point.py
src/xdesign/metrics/__init__.py
src/xdesign/metrics/coverage.py
src/xdesign/metrics/fullref.py
src/xdesign/metrics/standards.py
src/xdesign/phantom/__init__.py
src/xdesign/phantom/custom.py
src/xdesign/phantom/phantom.py
src/xdesign/phantom/standards.py
tests/DynamicRange[10, False].txt
tests/DynamicRange[10, True].txt
tests/HyperbolicConcentric[].txt
tests/Soil[].txt
tests/XDesignDefault[].txt
tests/cameraman.png
tests/cameraman_mixed1.png
tests/test_acquisition.py
tests/test_formats.py
tests/test_material.py
tests/test_metrics.py
tests/test_plot.py
